mercadolivresdk/__init__.py
mercadolivresdk/product_manager.py
mercadolivresdk/product_model.py
mercadolivresdk-0.0.2.dist-info/LICENSE
mercadolivresdk-0.0.2.dist-info/METADATA
mercadolivresdk-0.0.2.dist-info/WHEEL
mercadolivresdk-0.0.2.dist-info/top_level.txt
mercadolivresdk-0.0.2.dist-info/RECORD
