Metadata-Version: 2.1
Name: mercadolivresdk
Version: 0.0.2
Summary: biblioteca para integração com a API do Mercado Livre de forma facilitada
Home-page: https://github.com/Luc45-Pereira/mercadolivresdk
Author: Lucas Pereira de Lima
Author-email: lucaspereiradelima94@gmail.com
Classifier: Programming Language :: Python :: 3
Classifier: License :: OSI Approved :: MIT License
Classifier: Operating System :: OS Independent
Requires-Python: >=3.6
License-File: LICENSE
Requires-Dist: requests
Requires-Dist: pydantic
